inxs/__init__.py
inxs/cli.py
inxs/contrib.py
inxs/lib.py
inxs/lxml_utils.py
inxs-0.1b2.dev2.dist-info/DESCRIPTION.rst
inxs-0.1b2.dev2.dist-info/METADATA
inxs-0.1b2.dev2.dist-info/RECORD
inxs-0.1b2.dev2.dist-info/WHEEL
inxs-0.1b2.dev2.dist-info/entry_points.txt
inxs-0.1b2.dev2.dist-info/metadata.json
inxs-0.1b2.dev2.dist-info/top_level.txt
