Metadata-Version: 2.0
Name: inxs
Version: 0.1b2.dev2
Summary: A framework for XML transformations without boilerplate.
Home-page: https://github.com/funkyfuture/inxs
Author: Frank Sachsenheim
Author-email: funkyfuture@riseup.net
License: ISC license
Keywords: inxs xml processing transformation framework xslt not-xslt
Platform: UNKNOWN
Classifier: Development Status :: 4 - Beta
Classifier: Intended Audience :: Developers
Classifier: License :: OSI Approved :: ISC License (ISCL)
Classifier: Natural Language :: English
Classifier: Programming Language :: Python :: 3
Classifier: Programming Language :: Python :: 3 :: Only
Classifier: Programming Language :: Python :: 3.6
Classifier: Programming Language :: Python :: Implementation :: CPython
Classifier: Topic :: Text Processing :: Markup :: XML
Requires-Dist: dependency-injection
